image_label/common_bus.py
image_label/figure.py
image_label/gui.py
image_label/helpers.py
image_label/history.py
image_label/main.py
image_label/project.py
image_label/statechart.py
image_label/exporters/yolo.py
simple_image_label-0.0.1.1.dist-info/LICENSE
simple_image_label-0.0.1.1.dist-info/METADATA
simple_image_label-0.0.1.1.dist-info/WHEEL
simple_image_label-0.0.1.1.dist-info/entry_points.txt
simple_image_label-0.0.1.1.dist-info/top_level.txt
simple_image_label-0.0.1.1.dist-info/RECORD
