Metadata-Version: 2.1
Name: simple-image-label
Version: 0.0.1.1
Summary: Simple Python Tkinter image labelling app for ML purposes
Author: vkalyvayut-roboty-a-ne-chelovek
Project-URL: Homepage, https://github.com/vkalyvayut-roboty-a-ne-chelovek/image-label
Project-URL: Issues, https://github.com/vkalyvayut-roboty-a-ne-chelovek/image-label/issues
Requires-Python: >=3.10
License-File: LICENSE
Requires-Dist: miros
Requires-Dist: pillow
